sde/__init__.py
sde/__main__.py
sde/sde_class.py
sdeIU-0.0.1.dist-info/LICENSE
sdeIU-0.0.1.dist-info/METADATA
sdeIU-0.0.1.dist-info/WHEEL
sdeIU-0.0.1.dist-info/top_level.txt
sdeIU-0.0.1.dist-info/RECORD
