Metadata-Version: 2.1
Name: sdeIU
Version: 0.0.1
Summary: A simple tool for numerical stochastic differential equations
Author: Yuqiu Yang
Author-email: yuqiuy@smu.edu
Classifier: Programming Language :: Python :: 3 :: Only
Classifier: Natural Language :: English
Classifier: Intended Audience :: Science/Research
Requires-Python: >=3.9
License-File: LICENSE
Requires-Dist: matplotlib (==3.7.1)
Requires-Dist: numpy (==1.24.2)
Requires-Dist: tqdm (==4.65.0)
Requires-Dist: pandas (==2.0.0)
Requires-Dist: seaborn (==0.12.2)
